setup.cfg
setup.py
condecache/__init__.py
condecache/_six.py
condecache/cache.py
condecache/data_tools.py
condecache/errors.py
condecache.egg-info/PKG-INFO
condecache.egg-info/SOURCES.txt
condecache.egg-info/dependency_links.txt
condecache.egg-info/top_level.txt